Workbook

Sheet 使い方
B2: 自走型組織構築 KPI・進捗・資金繰り 管理フォーマット
B4: 目的 | C4: 毎日の動き・成果と仕組化の状況を記録し、進捗と今後の方向性を打ち出す。売上・利益目標をKPI化して達成率を可視化し、資金繰りまでつなげることで、メンバーが自ら考えて動く『自走型組織』の運営基盤にする。
B6: 運用サイクル
B7: 毎日 | C7: 『日次活動記録』に動き・成果・数値・課題・翌日アクションを記入（各自が入力）
B8: 毎週 | C8: 『週次進捗レビュー』で目標対比・学び・改善・方向性を確認（15〜30分のふりかえり）
B9: 毎月 | C9: 『KPI目標実績』に実績を入力→『ダッシュボード』で達成率を確認→『資金繰り表』を更新
B10: 四半期 | C10: 『仕組化チェック』で仕組み化・権限委譲の進捗を確認し、自走化の打ち手を決める
B12: 色の凡例
B13: 黄色のセル | C13: あなたが入力する場所（目標・実績・日々の記録など）
B14: 緑色のセル | C14: 自動計算（合計・小計）。編集しない
B15: 青文字 | C15: 手入力の数値
B16: 緑文字 | C16: 他シートからの自動参照
B17: 黒文字 | C17: 数式による計算結果
B19: シート構成
B20: ダッシュボード | C20: 全体サマリー。売上・利益の達成率と資金残高を一目で確認
B21: KPI目標実績 | C21: 売上・利益・活動KPIの年間目標と月次実績→達成率を自動計算
B22: 日次活動記録 | C22: 毎日の活動・成果・数値・課題・翌日アクションを記録
B23: 週次進捗レビュー | C23: 週ごとの目標対比・学び・改善・方向性を記録
B24: 資金繰り表 | C24: 月次の入出金と資金残高を管理（資金繰り）
B25: 仕組化チェック | C25: 仕組化・標準化・権限委譲の進捗（自走化）をチェック
B27: 年度 | C27: 2026

Sheet KPI目標実績
A1: KPI目標・実績・達成率
A2: 年間目標を入力し、毎月の実績を記入すると、累計と達成率が自動計算されます。（黄色＝入力）
A3: 項目 | B3: 単位 | C3: 年間目標 | D3: 4月 | E3: 5月 | F3: 6月 | G3: 7月 | H3: 8月 | I3: 9月 | J3: 10月 | K3: 11月 | L3: 12月 | M3: 1月 | N3: 2月 | O3: 3月 | P3: 累計実績 | Q3: 達成率
A4: 【売上・利益】
A5: 売上高 | B5: 円 | C5: 120000000 | D5: 8500000 | P5: =SUM(D5:O5) -> 8500000 | Q5: =IFERROR($P5/$C5,"") -> 0.070833333
A6: 売上原価 | B6: 円 | P6: =SUM(D6:O6) -> 0 | Q6: =IFERROR($P6/$C6,"")
A7: 売上総利益 | B7: 円 | C7: =C5-C6 -> 120000000 | D7: =D5-D6 -> 8500000 | E7: =E5-E6 -> 0 | F7: =F5-F6 -> 0 | G7: =G5-G6 -> 0 | H7: =H5-H6 -> 0 | I7: =I5-I6 -> 0 | J7: =J5-J6 -> 0 | ... O7: =O5-O6 -> 0 | P7: =SUM(D7:O7) -> 8500000 | Q7: =IFERROR($P7/$C7,"") -> 0.070833333
A8: 販売管理費 | B8: 円 | P8: =SUM(D8:O8) -> 0 | Q8: =IFERROR($P8/$C8,"")
A9: 営業利益 | B9: 円 | C9: =C7-C8 -> 120000000 | D9: =D7-D8 -> 8500000 | E9: =E7-E8 -> 0 | F9: =F7-F8 -> 0 | G9: =G7-G8 -> 0 | H9: =H7-H8 -> 0 | I9: =I7-I8 -> 0 | J9: =J7-J8 -> 0 | ... O9: =O7-O8 -> 0 | P9: =SUM(D9:O9) -> 8500000 | Q9: =IFERROR($P9/$C9,"") -> 0.070833333
A10: 営業利益率 | B10: % | C10: =IFERROR(C9/C5,"") -> 1 | D10: =IFERROR(D9/D5,"") -> 1 | E10: =IFERROR(E9/E5,"") | F10: =IFERROR(F9/F5,"") | G10: =IFERROR(G9/G5,"") | H10: =IFERROR(H9/H5,"") | I10: =IFERROR(I9/I5,"") | J10: =IFERROR(J9/J5,"") | ... O10: =IFERROR(O9/O5,"") | P10: =IFERROR($P9/$P5,"") -> 1 | Q10: =IFERROR($P10/$C10,"") -> 1
A11: 【活動KPI（先行指標）】
A12: 新規リード数 | B12: 件 | P12: =SUM(D12:O12) -> 0 | Q12: =IFERROR($P12/$C12,"")
A13: 商談数 | B13: 件 | P13: =SUM(D13:O13) -> 0 | Q13: =IFERROR($P13/$C13,"")
A14: 成約数 | B14: 件 | P14: =SUM(D14:O14) -> 0 | Q14: =IFERROR($P14/$C14,"")
A15: 成約率 | B15: % | C15: =IFERROR(C14/C13,"") | D15: =IFERROR(D14/D13,"") | E15: =IFERROR(E14/E13,"") | F15: =IFERROR(F14/F13,"") | G15: =IFERROR(G14/G13,"") | H15: =IFERROR(H14/H13,"") | I15: =IFERROR(I14/I13,"") | J15: =IFERROR(J14/J13,"") | ... O15: =IFERROR(O14/O13,"") | P15: =IFERROR($P14/$P13,"") | Q15: =IFERROR($P15/$C15,"")
A16: 客単価 | B16: 円 | C16: =IFERROR(C5/C14,"") | D16: =IFERROR(D5/D14,"") | E16: =IFERROR(E5/E14,"") | F16: =IFERROR(F5/F14,"") | G16: =IFERROR(G5/G14,"") | H16: =IFERROR(H5/H14,"") | I16: =IFERROR(I5/I14,"") | J16: =IFERROR(J5/J14,"") | ... O16: =IFERROR(O5/O14,"") | P16: =IFERROR($P5/$P14,"") | Q16: =IFERROR($P16/$C16,"")
A17: 【顧客・継続】
A18: 新規顧客数 | B18: 社 | P18: =SUM(D18:O18) -> 0 | Q18: =IFERROR($P18/$C18,"")
A19: 解約数 | B19: 社 | P19: =SUM(D19:O19) -> 0 | Q19: =IFERROR($P19/$C19,"")
A20: 顧客満足度(NPS等) | B20: pt | P20: =SUM(D20:O20) -> 0 | Q20: =IFERROR($P20/$C20,"")

Sheet ダッシュボード
A1: ダッシュボード
A2: =""&TEXT(使い方!$C$27,"0")&"年度サマリー（KPI目標実績・資金繰り表と自動連携）" -> 2026年度サマリー（KPI目標実績・資金繰り表と自動連携）
B4: 売上・利益（年間） | G4: 資金の状況
B5: 項目 | C5: 年間目標 | D5: 累計実績 | E5: 達成率 | G5: 項目 | H5: 金額(円)
B6: 売上高 | C6: =KPI目標実績!C5 -> 120000000 | D6: =KPI目標実績!P5 -> 8500000 | E6: =KPI目標実績!Q5 -> 0.070833333 | G6: 期首資金残高 | H6: =資金繰り表!$C$4 -> 5000000
B7: 売上総利益 | C7: =KPI目標実績!C7 -> 120000000 | D7: =KPI目標実績!P7 -> 8500000 | E7: =KPI目標実績!Q7 -> 0.070833333 | G7: 期末予定資金残高 | H7: =資金繰り表!$N$24 -> 6100000
B8: 営業利益 | C8: =KPI目標実績!C9 -> 120000000 | D8: =KPI目標実績!P9 -> 8500000 | E8: =KPI目標実績!Q9 -> 0.070833333 | G8: 年間営業収支 | H8: =資金繰り表!$O$17 -> 1100000
B9: 営業利益率 | C9: =KPI目標実績!C10 -> 1 | D9: =KPI目標実績!P10 -> 1 | E9: =KPI目標実績!Q10 -> 1 | G9: 最低月末残高 | H9: =MIN(資金繰り表!$C$24:$N$24) -> 6100000
B10: 成約数 | C10: =KPI目標実績!C14 -> 0 | D10: =KPI目標実績!P14 -> 0 | E10: =KPI目標実績!Q14
B11: 成約率 | C11: =KPI目標実績!C15 | D11: =KPI目標実績!P15 | E11: =KPI目標実績!Q15 | G11: ※ 最低月末残高がマイナスの月は資金ショートの恐れ
B14: 今後の方向性・重点アクション（毎月更新）
B15: ・ ・ ・

Sheet 日次活動記録
A1: 日次活動記録
A2: 毎日、その日の動き・成果・数値・課題・翌日アクションを記入（各自入力・黄色）
A3: 日付 | B3: 担当者 | C3: 主な活動・動き | D3: 成果・アウトプット | E3: 重要数値 (件数/金額) | F3: 課題・つまづき | G3: 明日のアクション
A4: 2026/04/01 | B4: 山田 | C4: 新規リード20件へアプローチ／既存A社と面談 | D4: A社が次回デモ確約・見込み80万 | E4: 架電15件 | F4: B社の返信が遅い | G4: B社へ再連絡・提案書修正

Sheet 週次進捗レビュー
A1: 週次進捗レビュー
A2: 週ごとの目標対比と学び・改善・方向性を記録。達成率は自動計算（黄色＝入力）
A3: 週 (開始日) | B3: 重点テーマ | C3: 今週の目標 (数値) | D3: 実績 (数値) | E3: 達成率 | F3: うまくいった事 | G3: 課題・学び | H3: 来週の改善 アクション | I3: 方向性メモ
A4: 2026/04/06 | B4: 新規開拓強化 | C4: 50 | D4: 42 | E4: =IFERROR(D4/C4,"") -> 0.84 | F4: 面談数が過去最高 | G4: 提案の質にばらつき | H4: トークスクリプト整備 | I4: 開拓チームに権限委譲を検討
E5: =IFERROR(D5/C5,"")
E6: =IFERROR(D6/C6,"")
E7: =IFERROR(D7/C7,"")
E8: =IFERROR(D8/C8,"")
E9: =IFERROR(D9/C9,"")
E10: =IFERROR(D10/C10,"")
E11: =IFERROR(D11/C11,"")
E12: =IFERROR(D12/C12,"")
E13: =IFERROR(D13/C13,"")
E14: =IFERROR(D14/C14,"")
E15: =IFERROR(D15/C15,"")
E16: =IFERROR(D16/C16,"")
... E29: =IFERROR(D29/C29,"")

Sheet 資金繰り表
A1: 資金繰り表（月次）
A2: 月初残高・入出金を入力すると、営業収支・翌月繰越・資金残高が自動計算されます（黄色＝入力）
B3: 項目 | C3: 4月 | D3: 5月 | E3: 6月 | F3: 7月 | G3: 8月 | H3: 9月 | I3: 10月 | J3: 11月 | K3: 12月 | L3: 1月 | M3: 2月 | N3: 3月 | O3: 年間合計
B4: 前月繰越（月初資金） | C4: 5000000 | D4: =C24 -> 6100000 | E4: =D24 -> 6100000 | F4: =E24 -> 6100000 | G4: =F24 -> 6100000 | H4: =G24 -> 6100000 | I4: =H24 -> 6100000 | J4: =I24 -> 6100000 | K4: =J24 -> 6100000 | ... N4: =M24 -> 6100000 | O4: =C4 -> 5000000
B5: 【営業収入】
B6: 現金売上 | C6: 3000000 | O6: =SUM(C6:N6) -> 3000000
B7: 売掛金回収 | C7: 5500000 | O7: =SUM(C7:N7) -> 5500000
B8: その他営業収入 | O8: =SUM(C8:N8) -> 0
B9: 営業収入 合計 | C9: =SUM(C6:C8) -> 8500000 | D9: =SUM(D6:D8) -> 0 | E9: =SUM(E6:E8) -> 0 | F9: =SUM(F6:F8) -> 0 | G9: =SUM(G6:G8) -> 0 | H9: =SUM(H6:H8) -> 0 | I9: =SUM(I6:I8) -> 0 | J9: =SUM(J6:J8) -> 0 | ... N9: =SUM(N6:N8) -> 0 | O9: =SUM(C9:N9) -> 8500000
B10: 【営業支出】
B11: 仕入・外注費 | C11: 2500000 | O11: =SUM(C11:N11) -> 2500000
B12: 人件費 | C12: 3500000 | O12: =SUM(C12:N12) -> 3500000
B13: 家賃・地代 | C13: 600000 | O13: =SUM(C13:N13) -> 600000
B14: その他経費 | C14: 800000 | O14: =SUM(C14:N14) -> 800000
B15: 税金・社会保険 | O15: =SUM(C15:N15) -> 0
B16: 営業支出 合計 | C16: =SUM(C11:C15) -> 7400000 | D16: =SUM(D11:D15) -> 0 | E16: =SUM(E11:E15) -> 0 | F16: =SUM(F11:F15) -> 0 | G16: =SUM(G11:G15) -> 0 | H16: =SUM(H11:H15) -> 0 | I16: =SUM(I11:I15) -> 0 | J16: =SUM(J11:J15) -> 0 | ... N16: =SUM(N11:N15) -> 0 | O16: =SUM(C16:N16) -> 7400000
B17: 営業収支（収入-支出） | C17: =C9-C16 -> 1100000 | D17: =D9-D16 -> 0 | E17: =E9-E16 -> 0 | F17: =F9-F16 -> 0 | G17: =G9-G16 -> 0 | H17: =H9-H16 -> 0 | I17: =I9-I16 -> 0 | J17: =J9-J16 -> 0 | ... N17: =N9-N16 -> 0 | O17: =SUM(C17:N17) -> 1100000
B18: 【財務・投資】
B19: 借入金（入金） | O19: =SUM(C19:N19) -> 0
B20: 借入返済（出金） | O20: =SUM(C20:N20) -> 0
B21: 設備投資等（出金） | O21: =SUM(C21:N21) -> 0
B22: 財務・投資 収支 | C22: =C19-C20-C21 -> 0 | D22: =D19-D20-D21 -> 0 | E22: =E19-E20-E21 -> 0 | F22: =F19-F20-F21 -> 0 | G22: =G19-G20-G21 -> 0 | H22: =H19-H20-H21 -> 0 | I22: =I19-I20-I21 -> 0 | J22: =J19-J20-J21 -> 0 | ... N22: =N19-N20-N21 -> 0 | O22: =SUM(C22:N22) -> 0
B23: 当月収支合計 | C23: =C17+C22 -> 1100000 | D23: =D17+D22 -> 0 | E23: =E17+E22 -> 0 | F23: =F17+F22 -> 0 | G23: =G17+G22 -> 0 | H23: =H17+H22 -> 0 | I23: =I17+I22 -> 0 | J23: =J17+J22 -> 0 | ... N23: =N17+N22 -> 0 | O23: =SUM(C23:N23) -> 1100000
B24: 翌月繰越（月末資金） | C24: =C4+C23 -> 6100000 | D24: =D4+D23 -> 6100000 | E24: =E4+E23 -> 6100000 | F24: =F4+F23 -> 6100000 | G24: =G4+G23 -> 6100000 | H24: =H4+H23 -> 6100000 | I24: =I4+I23 -> 6100000 | J24: =J4+J23 -> 6100000 | ... N24: =N4+N23 -> 6100000 | O24: =N24 -> 6100000

Sheet 仕組化チェック
A1: 仕組化・自走化チェック
A2: 業務の標準化・マニュアル化・権限委譲の進捗を管理。進捗率は自動集計（黄色＝入力）
A3: 領域 | B3: 仕組化する項目 | C3: 担当 | D3: 状態 | E3: 進捗率 | F3: 期限 | G3: メモ・次の一手
A4: 営業 | B4: 営業トークスクリプト・提案書テンプレの標準化 | D4: 進行中 | E4: 0.4 | F4: 2026/06/30 | G4: 属人化の解消。まず売上上位者の型を言語化
A5: 営業 | B5: 顧客管理・商談パイプラインの見える化 | D5: 未着手 | E5: 0 | F5: 2026/07/31
A6: マーケ | B6: リード獲得〜育成の仕組み化 | D6: 未着手 | E6: 0 | F6: 2026/09/30
A7: 業務 | B7: 定型業務のマニュアル化・チェックリスト | D7: 進行中 | E7: 0.3 | F7: 2026/08/31 | G7: 入社1週間で回せる状態が目標
A8: 業務 | B8: 日次・週次の報告フォーマット統一 | D8: 完了 | E8: 1 | F8: 2026/04/30 | G8: 本フォーマットで運用開始
A9: 組織 | B9: 役割分担・権限委譲ルールの明文化 | D9: 未着手 | E9: 0 | F9: 2026/10/31 | G9: 自走化の要。決裁範囲を定義
A10: 組織 | B10: KPI連動の評価・振り返りの仕組み | D10: 進行中 | E10: 0.2 | F10: 2026/09/30
A11: 数値 | B11: 月次でKPI・資金繰りをレビューする会議体 | D11: 進行中 | E11: 0.5 | F11: 2026/05/31 | G11: 本ツールを用いた月次会議を定例化
A19: 全体進捗（平均） | E19: =IFERROR(AVERAGE(E4:E17),0) -> 0.3
A20: 完了項目数 | E20: =COUNTIF(D4:D17,"完了") -> 1
